Workbook

Sheet Resumen
A1: Reclasificación tax `p_iva_exento` — sample agrupado por proveedor
A2: Fuente: dump Holded 2026-05-11 — purchase.jsonl + purchaserefund.jsonl. Total: 111 proveedores, 2.146 docs, 439.122,30 € en líneas con tax key p_iva_exento.
A4: Cubetas de decisión
A5: Cubeta | B5: Tax destino | C5: Cuándo aplica
A6: A. Exento real Art.20 | B6: 0% EXEMPT OP (id=95) | C6: Sanidad, vales empleados, financiero, notarial, admin pública, alquileres genuinos exentos.
A7: B. Reverse charge intracom UE | B7: 21% RC (id=112) | C7: Proveedor con NIF UE válido (IE/DE/NL/...). Lookup directo en l10n_es.
A8: C. Reverse charge extra-UE | B8: 21% RC (id=112) + flag review | C8: SaaS US/AU/HK/CN/UK/NO. Fase 5.3 puede requerir crear `21% RC ExtraUE`.
A9: D. Olvido del operador en Holded | B9: 21% G u otro tipo real | C9: Factura que debía llevar IVA repercutido normal — Holded recibió `p_iva_exento` por error.
A11: Distribución por bucket
A12: Bucket | B12: Suppliers | C12: Docs | D12: EUR exento
A13: 1. ES (España) | B13: =COUNTIF(Proveedores!A:A,"ES") | C13: =SUMIF(Proveedores!A:A,"ES",Proveedores!E:E) | D13: =SUMIF(Proveedores!A:A,"ES",Proveedores!G:G)
A14: 2. UE no-ES (intracom) | B14: =COUNTIF(Proveedores!A:A,"UE_NO_ES") | C14: =SUMIF(Proveedores!A:A,"UE_NO_ES",Proveedores!E:E) | D14: =SUMIF(Proveedores!A:A,"UE_NO_ES",Proveedores!G:G)
A15: 3. Extra-UE (SaaS) | B15: =COUNTIF(Proveedores!A:A,"EXTRA_UE") | C15: =SUMIF(Proveedores!A:A,"EXTRA_UE",Proveedores!E:E) | D15: =SUMIF(Proveedores!A:A,"EXTRA_UE",Proveedores!G:G)
A16: 4. Sin país | B16: =COUNTIF(Proveedores!A:A,"SIN_PAIS") | C16: =SUMIF(Proveedores!A:A,"SIN_PAIS",Proveedores!E:E) | D16: =SUMIF(Proveedores!A:A,"SIN_PAIS",Proveedores!G:G)
A17: TOTAL | B17: =SUM(B13:B16) | C17: =SUM(C13:C16) | D17: =SUM(D13:D16)
A20: Distribución por decisión operador (rellena automáticamente al completar columna 'decision')
A21: Decisión | B21: Suppliers | C21: EUR exento
A22: A (Art.20 exento) | B22: =COUNTIF(Proveedores!N:N,"A*") | C22: =SUMIF(Proveedores!N:N,"A*",Proveedores!G:G)
A23: B (RC intracom UE) | B23: =COUNTIF(Proveedores!N:N,"B*") | C23: =SUMIF(Proveedores!N:N,"B*",Proveedores!G:G)
A24: C (RC extra-UE) | B24: =COUNTIF(Proveedores!N:N,"C*") | C24: =SUMIF(Proveedores!N:N,"C*",Proveedores!G:G)
A25: D (olvido 21%) | B25: =COUNTIF(Proveedores!N:N,"D*") | C25: =SUMIF(Proveedores!N:N,"D*",Proveedores!G:G)
A26: Otra/pendiente | B26: =COUNTIF(Proveedores!N:N,"")-1 | C26: =SUMIF(Proveedores!N:N,"",Proveedores!G:G)

Sheet Proveedores
A1: Bucket | B1: Proveedor | C1: País | D1: Code/VAT | E1: Docs | F1: Líneas | G1: EUR exento líneas | H1: EUR total docs | I1: Desde | J1: Hasta | K1: Sugerencia tax_id | L1: Sugerencia label | M1: Razón heurística | N1: DECISIÓN (A/B/C/D) | O1: Notas operador | P1: Top descripciones | Q1: Sample docNumbers
A2: ES | B2: CHEQUE DEUJENER S.A. | C2: ES | D2: A78887049 | E2: 177 | F2: 300 | G2: 93074.45 | H2: 96098.82 | I2: 2018 | J2: 2025 | K2: 95 | L2: 0% EXEMPT | M2: Vales empleados Art.20 | P2: COMPRAS SERVICIOS TIPO EXENTO | Cheque Deujener | Cheque Deujener Transporte | Q2: 1818181 (438.19€) | 2804423 (102.42€)
A3: ES | B3: PLUXEE ESPAÑA SAU | C3: ES | D3: A78604113 | E3: 21 | F3: 24 | G3: 20320 | H3: 20627.9 | I3: 2024 | J3: 2026 | K3: 95 | L3: 0% EXEMPT | M3: Vales empleados Art.20 | P3: Pluxee | Importe de tarjetas | Prestación de servicio | Q3: 1481803 (1522.69€) | 1470980 (1522.69€)
A4: ES | B4: ARVAL SERVICE LEASE S.A. | C4: ES | D4: A81573479 | E4: 96 | F4: 96 | G4: 19156.02 | H4: 41171.66 | I4: 2019 | J4: 2026 | L4: REVISAR | M4: Renting: ¿exento o 21% genuino? | P4: Arval | COMPRAS SERVICIOS TIPO EXENTO | Servicio de Renting | Q4: 1901055838 (484€) | 1900980975 (484€)
A5: ES | B5: LYNK & CO SALES SPAIN SL | C5: ES | D5: B05398037 | E5: 46 | F5: 46 | G5: 15155.25 | H5: 30310.5 | I5: 2022 | J5: 2025 | L5: DECIDIR | M5: ES sin tax explicito: ¿olvido 21% o Art.20? | P5: LYNK & CO | LYNK & CO (diciembre) | LYNK & CO (MAYO) | Q5: 1800003425 (665.5€) | 1800003079 (665.5€)
A6: ES | B6: LEASE PLAN SERVICIOS S.A. | C6: ES | D6: A78007473 | E6: 54 | F6: 59 | G6: 14253.74 | H6: 51577.06 | I6: 2018 | J6: 2022 | L6: REVISAR | M6: Renting: ¿exento o 21% genuino? | P6: COMPRAS SERVICIOS TIPO EXENTO | Lease Plan | Q6: 14449538 (1190.14€) | 13600963 (495.13€)
A7: ES | B7: QUIRON PREVENCION S.L.U. | C7: ES | D7: B64076482 | E7: 72 | F7: 83 | G7: 7396.87 | H7: 8126.89 | I7: 2018 | J7: 2026 | K7: 95 | L7: 0% EXEMPT | M7: Art.20 sanidad/seguros | P7: Quiron Prevencion | COMPRAS SERVICIOS TIPO EXENTO | COMPRAS SERVICIOS TIPO 21% | Q7: 0118502722 (167.46€) | 0118128937 (30€)
A8: ES | B8: MOLDTRANS S.L. | C8: ES | D8: B08569089 | E8: 77 | F8: 80 | G8: 7382.83 | H8: 7933.3 | I8: 2018 | J8: 2022 | L8: DECIDIR | M8: ES sin tax explicito: ¿olvido 21% o Art.20? | P8: COMPRAS SERVICIOS TIPO EXENTO | Moldtrans | Moldtrans (Agosto) | Q8: BCNV135188 (496.34€) | BCNV300655 (2.54€)
A9: ES | B9: PORTOLES CARILLA, ANA | C9: ES | D9: 44999256D | E9: 11 | F9: 11 | G9: 5470.67 | H9: 4650.08 | I9: 2018 | J9: 2019 | L9: DECIDIR | M9: ES sin tax explicito: ¿olvido 21% o Art.20? | P9: COMPRAS SERVICIOS TIPO EXENTO | Q9: F015 (450€) | F014 (600€)
A10: ES | B10: EVA MELUS FIERRO | C10: ES | D10: 52208721D | E10: 11 | F10: 11 | G10: 4200 | H10: 3570 | I10: 2018 | J10: 2019 | L10: DECIDIR | M10: ES sin tax explicito: ¿olvido 21% o Art.20? | P10: COMPRAS SERVICIOS TIPO EXENTO | Q10: 293 (382.5€) | 288 (382.5€)
A11: ES | B11: AMAZON EU S.A.R.L | C11: ES | D11: W0184081H | E11: 6 | F11: 6 | G11: 3315.53 | H11: 3315.53 | I11: 2022 | J11: 2026 | L11: DECIDIR | M11: ES sin tax explicito: ¿olvido 21% o Art.20? | P11: Amazon | PORT-069 HP Laptop PORT-069 EliteBook 840 G11 14" Intel Core | Amazon eGift Card - You're the best. (Animated) | Q11: ES217DB4AEUI (300€) | ES315Z9MAEUI (315€)
A12: ES | B12: REGISTRARMARCAS, S.L | C12: ES | D12: B64938624 | E12: 5 | F12: 5 | G12: 2896.44 | H12: 3792.98 | I12: 2022 | J12: 2022 | L12: DECIDIR | M12: ES sin tax explicito: ¿olvido 21% o Art.20? | P12: RegistrarMarcas | REGISTRAR MARCA DENOMINATIVA FARMACLOUD | REGISTRAR MARCA FIGURATIVA FARMACLOUD | Q12: 4188 (378.99€) | 4189 (378.99€)
A13: ES | B13: VUELING AIRLINES S.A. | C13: ES | D13: A63422141 | E13: 28 | F13: 32 | G13: 2169.16 | H13: 6240.72 | I13: 2018 | J13: 2025 | L13: REVISAR | M13: Transporte: a veces lleva IVA 10% | P13: COMPRAS SERVICIOS TIPO EXENTO | Vueling (Geraldine Garcia) | COMPRAS BIENES TIPO EXENTO | Q13: 905771 (199.88€) | 138937 (61.17€)
A14: ES | B14: NACEX A.R.B.94 S.L. | C14: ES | D14: B60686169 | E14: 47 | F14: 47 | G14: 2070.71 | H14: 20405.55 | I14: 2022 | J14: 2025 | L14: DECIDIR | M14: ES sin tax explicito: ¿olvido 21% o Art.20? | P14: Nacex | Q14: S2890 (8.56€) | A106345 (1033.93€)
A15: ES | B15: FED.FARMACEUTICA S.COOP.CL. | C15: ES | D15: F08173395 | E15: 11 | F15: 11 | G15: 1973.19 | H15: 1598.28 | I15: 2018 | J15: 2025 | L15: DECIDIR | M15: ES sin tax explicito: ¿olvido 21% o Art.20? | P15: COMPRAS SERVICIOS TIPO EXENTO | Fede | Q15: VN180082235 (-66.91€) | VN180065249 (66.91€)
A16: ES | B16: ASSOCIACIO DEL CLUSTER BELLESA DE CATALUNYA | C16: ES | D16: G66286105 | E16: 1 | F16: 1 | G16: 1200 | H16: 1200 | I16: 2018 | J16: 2018 | L16: DECIDIR | M16: ES sin tax explicito: ¿olvido 21% o Art.20? | P16: COMPRAS SERVICIOS TIPO EXENTO | Q16: 20180147 (1200€)
A17: ES | B17: JAVIER FERRER GONZALEZ | C17: ES | D17: 47658995M | E17: 1 | F17: 1 | G17: 1027.95 | H17: 955.99 | I17: 2019 | J17: 2019 | L17: DECIDIR | M17: ES sin tax explicito: ¿olvido 21% o Art.20? | P17: COMPRAS SERVICIOS TIPO EXENTO | Q17: 2019030010 (955.99€)
A18: ES | B18: AUTOMOBILS A R MOTORS SL (AR MOTORS AUTOMOBILS A.R. MOTORS S.L.) | C18: ES | D18: B08126021 | E18: 2 | F18: 2 | G18: 1000 | H18: 1000 | I18: 2025 | J18: 2025 | L18: DECIDIR | M18: ES sin tax explicito: ¿olvido 21% o Art.20? | P18: Vehículo Geraldine (FIANZA) | Q18: 104907 (500€) | 110225 (500€)
A19: ES | B19: CODELY ENSEÑA Y ENTRETIENE, S.L | C19: ES | D19: B67560615 | E19: 1 | F19: 1 | G19: 956 | H19: 956 | I19: 2020 | J19: 2020 | L19: DECIDIR | M19: ES sin tax explicito: ¿olvido 21% o Art.20? | P19: COMPRAS SERVICIOS TIPO EXENTO | Q19: 2020030150 (956€)
... A24: ES | B24: DURAN SINDREU S.L.P. | C24: ES | D24: B62340716 | E24: 3 | F24: 10 | G24: 661.4 | H24: 661.4 | I24: 2020 | J24: 2021 | L24: DECIDIR | M24: ES sin tax explicito: ¿olvido 21% o Art.20? | P24: COMPRAS SERVICIOS TIPO EXENTO | COMPRAS BIENES TIPO EXENTO | Q24: 3200029 (-39.89€) | 3200016 (350€)
A25: ES | B25: J. ISERN PATENTES Y MARCAS S.L. | C25: ES | D25: B62748827 | E25: 2 | F25: 2 | G25: 587.12 | H25: 2728.82 | I25: 2022 | J25: 2022 | K25: 95 | L25: 0% EXEMPT | M25: Servicios juridicos/notariales Art.20 | P25: Isern (Mayo) | Q25: B10168 (1364.4099999999999€) | B10179 (1364.4099999999999€)
A26: ES | B26: CAIXABANK S.A. | C26: ES | D26: A08663619 | E26: 5 | F26: 5 | G26: 407.5 | H26: 718.19 | I26: 2018 | J26: 2018 | K26: 95 | L26: 0% EXEMPT | M26: Servicios financieros Art.20 | P26: COMPRAS SERVICIOS TIPO EXENTO | Q26: 26022018 (82.96€) | 19022018 (280.11€)
A27: ES | B27: JOSEP M. BORT CALDES | C27: ES | D27: 46623250L | E27: 1 | F27: 1 | G27: 270 | H27: 886.68 | I27: 2019 | J27: 2019 | L27: DECIDIR | M27: ES sin tax explicito: ¿olvido 21% o Art.20? | P27: COMPRAS SERVICIOS TIPO EXENTO | Q27: 1262019 (886.68€)
A28: ES | B28: PONS IP, S.A | C28: ES | D28: A28750891 | E28: 3 | F28: 3 | G28: 268.35 | H28: 1609.03 | I28: 2023 | J28: 2026 | K28: 95 | L28: 0% EXEMPT | M28: Servicios juridicos/notariales Art.20 | P28: Pons IP | Tasas OEPM CI08 - Oposición contra marca nacional nº 4352087 | Q28: FV231009705 (231.86€) | FV231003931 (900.4200000000001€)
A29: ES | B29: SIMFONY | C29: ES | D29: FR06834643579 | E29: 1 | F29: 1 | G29: 237 | H29: 237 | I29: 2021 | J29: 2021 | L29: DECIDIR | M29: ES sin tax explicito: ¿olvido 21% o Art.20? | P29: COMPRAS SERVICIOS TIPO 21% | Q29: IN2105108 (237€)
A30: ES | B30: AMAZON.ES COMPRA | C30: ES | D30: ESW0184081H | E30: 1 | F30: 1 | G30: 225 | H30: 225 | I30: 2018 | J30: 2018 | L30: DECIDIR | M30: ES sin tax explicito: ¿olvido 21% o Art.20? | P30: COMPRAS SERVICIOS TIPO EXENTO | Q30: 16523011 (225€)
A31: ES | B31: KLM Royal Dutch Airlines, | C31: ES | D31: W0031001A | E31: 1 | F31: 1 | G31: 215.95 | H31: 215.95 | I31: 2024 | J31: 2024 | L31: REVISAR | M31: Transporte: a veces lleva IVA 10% | P31: KLM | Q31: KLES0021922444 (215.95€)
A32: ES | B32: AIR EUROPA LINEAS AEREAS SAU | C32: ES | D32: A07129430 | E32: 2 | F32: 2 | G32: 187.43 | H32: 188.65 | I32: 2018 | J32: 2019 | L32: REVISAR | M32: Transporte: a veces lleva IVA 10% | P32: COMPRAS SERVICIOS TIPO EXENTO | Q32: FF223625 (93.65€) | FF470952 (95€)
A33: ES | B33: RYANAIR LTED. | C33: ES | D33: W0071513F | E33: 6 | F33: 6 | G33: 184.97 | H33: 275.81 | I33: 2018 | J33: 2024 | L33: REVISAR | M33: Transporte: a veces lleva IVA 10% | P33: COMPRAS SERVICIOS TIPO EXENTO | Ryanair (Geraldine Garcia) | Vueling (Geraldine Garcia) | Q33: 1008689365 (7€) | 1008689408 (7€)
A34: ES | B34: SARA BRAVO DE SOTO (FANTASTICA BUHARDILLA) | C34: ES | D34: 17749926K | E34: 1 | F34: 1 | G34: 162.46 | H34: 162.46 | I34: 2023 | J34: 2023 | L34: DECIDIR | M34: ES sin tax explicito: ¿olvido 21% o Art.20? | P34: FANTASTICA BUHARDILLA (SARA BRAVO) | Q34: 2023103 (162.46€)
A35: ES | B35: PRINTCARRIER.COM GMBH | C35: ES | D35: DE815758704 | E35: 2 | F35: 2 | G35: 112.66 | H35: 112.66 | I35: 2021 | J35: 2021 | L35: DECIDIR | M35: ES sin tax explicito: ¿olvido 21% o Art.20? | P35: COMPRAS SERVICIOS TIPO 21% | Q35: ED00000085 (56.33€) | ED00000086 (56.33€)
A36: ES | B36: BOLETIN OFICIAL DEL ESTADO | C36: ES | D36: Q2811001C | E36: 2 | F36: 2 | G36: 86.38 | H36: 86.38 | I36: 2020 | J36: 2021 | K36: 95 | L36: 0% EXEMPT | M36: Admin publica - no sujeto | P36: COMPRAS BIENES TIPO EXENTO | COMPRAS SERVICIOS TIPO EXENTO | Q36: B40535659 (57.94€) | B41563035 (28.44€)
A37: ES | B37: RHENUS LOGISTICS S.A.U. | C37: ES | D37: A08211989 | E37: 13 | F37: 13 | G37: 75.16 | H37: 75.16 | I37: 2019 | J37: 2021 | L37: DECIDIR | M37: ES sin tax explicito: ¿olvido 21% o Art.20? | P37: COMPRAS SERVICIOS TIPO EXENTO | Q37: 040324559 (-23.74€) | 0401371396 (23.74€)
A38: ES | B38: SOCIEDAD ESTATAL CORREOS Y TELEGRAFOS S.A. | C38: ES | D38: A83052407 | E38: 10 | F38: 10 | G38: 66.08 | H38: 68.06 | I38: 2018 | J38: 2018 | L38: DECIDIR | M38: ES sin tax explicito: ¿olvido 21% o Art.20? | P38: COMPRAS SERVICIOS TIPO EXENTO | Q38: 5000010 (4.4€) | 5F00001 (22€)
A39: ES | B39: RENFE OPERADORA | C39: ES | D39: Q2801659J | E39: 7 | F39: 7 | G39: 43.95 | H39: -186.89 | I39: 2018 | J39: 2020 | L39: REVISAR | M39: Transporte: a veces lleva IVA 10% | P39: COMPRAS SERVICIOS TIPO EXENTO | COMPRAS BIENES TIPO EXENTO | Q39: VR550675 (-124.19€) | 687770 (-38.4€)
A40: ES | B40: RENFE VIAJEROS S.M.E., S.A | C40: ES | D40: A86868189 | E40: 9 | F40: 9 | G40: 26.6 | H40: 279.8 | I40: 2021 | J40: 2024 | L40: REVISAR | M40: Transporte: a veces lleva IVA 10% | P40: Renfe (Carles Sebastian) | Renfe Viajeros | Renfe (Juan Tramullas) | Q40: VR00000000960256 (-25.5€) | VJ00000014549802 (20.95€)
A41: ES | B41: MENSAT S.L. | C41: ES | D41: B60032869 | E41: 1 | F41: 1 | G41: 19.9 | H41: 129.8 | I41: 2019 | J41: 2019 | L41: DECIDIR | M41: ES sin tax explicito: ¿olvido 21% o Art.20? | P41: COMPRAS SERVICIOS TIPO EXENTO | Q41: A75725 (129.8€)
A42: ES | B42: NOTARÍA CUZCO 3 C.B | C42: ES | D42: E01747294 | E42: 2 | F42: 2 | G42: 17.04 | H42: 434.12 | I42: 2021 | J42: 2021 | L42: DECIDIR | M42: ES sin tax explicito: ¿olvido 21% o Art.20? | P42: COMPRAS SERVICIOS TIPO EXENTO | Q42: O04150 (359.64€) | O04151 (74.48€)
A43: ES | B43: DIEZ ARRANZ, ANA | C43: ES | D43: 13102882N | E43: 2 | F43: 2 | G43: 12.62 | H43: 1242.04 | I43: 2021 | J43: 2023 | L43: DECIDIR | M43: ES sin tax explicito: ¿olvido 21% o Art.20? | P43: COMPRAS SERVICIOS TIPO 0% | Notario Diez Arranz | Q43: A0001458 (199.42000000000002€) | A0001265 (1042.62€)
A44: ES | B44: BANCO DE SANTANDER S.A. | C44: ES | D44: A39000013 | E44: 5 | F44: 5 | G44: 3.5 | H44: 10.4 | I44: 2021 | J44: 2021 | K44: 95 | L44: 0% EXEMPT | M44: Servicios financieros Art.20 | P44: COMPRAS SERVICIOS TIPO EXENTO | Q44: F2021216XBBBBBV (3.2399999999999998€) | F2021181RBBBBRN (1.79€)
A45: ES | B45: NOTARIA DIAGONAL 550 SCP | C45: ES | D45: J66181579 | E45: 1 | F45: 1 | G45: 2.4 | H45: 84.57 | I45: 2021 | J45: 2021 | K45: 95 | L45: 0% EXEMPT | M45: Servicios juridicos/notariales Art.20 | P45: COMPRAS SERVICIOS TIPO EXENTO | Q45: A4001475 (84.57000000000001€)
A46: UE_NO_ES | B46: GOOGLE IRELAND LIMITED | C46: IE | D46: IE6388047V | E46: 100 | F46: 100 | G46: 95670.12 | H46: 95670.12 | I46: 2018 | J46: 2021 | K46: 112 | L46: 21% RC | M46: Intracom UE B2B servicios | P46: COMPRAS SERVICIOS TIPO 21% | Q46: 3533347939 (2788.18€) | 3537661771 (160€)
A47: UE_NO_ES | B47: ADOBE SYSTEMS SOFTWARE IRELAND LTD | C47: IE | D47: IE6364992H | E47: 67 | F47: 67 | G47: 11703.17 | H47: 11703.17 | I47: 2018 | J47: 2021 | K47: 112 | L47: 21% RC | M47: Intracom UE B2B servicios | P47: COMPRAS SERVICIOS TIPO 21% | Q47: IEE2018006000280 (279.96€) | IEE2019000004746 (9.99€)
A48: UE_NO_ES | B48: MICROSOFT IRELAND OPERATIONS LTD | C48: IE | D48: IE8256796U | E48: 39 | F48: 39 | G48: 3247.84 | H48: 3247.84 | I48: 2018 | J48: 2021 | K48: 112 | L48: 21% RC | M48: Intracom UE B2B servicios | P48: COMPRAS SERVICIOS TIPO 21% | Q48: E05006UIYO (70.4€) | E05006NBYA (70.4€)
A49: UE_NO_ES | B49: CRELLO LIMITED | C49: CY | D49: CY10384877E | E49: 2 | F49: 2 | G49: 2762.03 | H49: 2762.03 | I49: 2021 | J49: 2021 | K49: 112 | L49: 21% RC | M49: Intracom UE B2B servicios | P49: COMPRAS SERVICIOS TIPO 21% | Q49: 4224 (1413.84€) | 3786 (1348.19€)
A50: UE_NO_ES | B50: LOGMEIN INC. | C50: IE | D50: IE9834481A | E50: 7 | F50: 7 | G50: 2369.78 | H50: 2369.78 | I50: 2018 | J50: 2020 | K50: 112 | L50: 21% RC | M50: Intracom UE B2B servicios | P50: COMPRAS SERVICIOS TIPO 21% | Q50: 2765828 (386.54€) | 5841501 (35.37€)
A51: UE_NO_ES | B51: PINGDOM AB | C51: SE | D51: SE556680747401 | E51: 35 | F51: 36 | G51: 1748.68 | H51: 1748.68 | I51: 2018 | J51: 2020 | K51: 112 | L51: 21% RC | M51: Intracom UE B2B servicios | P51: COMPRAS SERVICIOS TIPO 21% | Q51: 2860707 (50.68€) | 2840061 (50.8€)
A52: UE_NO_ES | B52: JETBRAINS SRO | C52: CZ | D52: CZ26502275 | E52: 6 | F52: 6 | G52: 1548.15 | H52: 1548.15 | I52: 2019 | J52: 2021 | K52: 112 | L52: 21% RC | M52: Intracom UE B2B servicios | P52: COMPRAS SERVICIOS TIPO 21% | Q52: 4458869 (199€) | INVCZ1772174 (199€)
A53: UE_NO_ES | B53: PRINTCARRIER.COM /WINTERHAUSEN | C53: DE | D53: DE256458550 | E53: 15 | F53: 15 | G53: 1317.71 | H53: 1317.71 | I53: 2018 | J53: 2020 | K53: 112 | L53: 21% RC | M53: Intracom UE B2B servicios | P53: COMPRAS SERVICIOS TIPO 21% | COMPRAS BIENES TIPO GEN. | Q53: ED00001005 (34.85€) | ED00001003 (48.05€)
A54: UE_NO_ES | B54: HETZNER ONLINE AG | C54: DE | D54: DE812871812 | E54: 23 | F54: 23 | G54: 1239.19 | H54: 1239.19 | I54: 2018 | J54: 2019 | K54: 112 | L54: 21% RC | M54: Intracom UE B2B servicios | P54: COMPRAS SERVICIOS TIPO 21% | Q54: R0008937082 (42.02€) | R0008815678 (42.02€)
A55: UE_NO_ES | B55: LASTPASS IRELAND LIMITED | C55: IE | D55: IE3727972WH | E55: 1 | F55: 1 | G55: 1009.43 | H55: 1009.43 | I55: 2021 | J55: 2021 | K55: 112 | L55: 21% RC | M55: Intracom UE B2B servicios | P55: COMPRAS SERVICIOS TIPO 21% | Q55: INLASSYCCL7L60835730 (1009.43€)
... A75: EXTRA_UE | B75: ATLASSIAN PTY LTD | C75: AU | D75: AUEU372001951 | E75: 100 | F75: 100 | G75: 12651.24 | H75: 12651.24 | I75: 2018 | J75: 2021 | K75: 112 | L75: 21% RC | M75: Extra-UE SaaS (review: posible nuevo tax) | P75: COMPRAS SERVICIOS TIPO 21% | Q75: AT67822350 (160.77€) | AT67822366 (21.88€)
A76: EXTRA_UE | B76: NEXMO INC | C76: US | E76: 126 | F76: 126 | G76: 10560 | H76: 10560 | I76: 2018 | J76: 2021 | K76: 112 | L76: 21% RC | M76: Extra-UE SaaS (review: posible nuevo tax) | P76: COMPRAS SERVICIOS TIPO 21% | VENTAS SERVICIOS TIPO GEN. | Q76: 125853 (10€) | 125850 (10€)
A77: EXTRA_UE | B77: GODADDY | C77: US | D77: USEU826010755 | E77: 29 | F77: 29 | G77: 3864.27 | H77: 3864.27 | I77: 2018 | J77: 2021 | K77: 112 | L77: 21% RC | M77: Extra-UE SaaS (review: posible nuevo tax) | P77: COMPRAS SERVICIOS TIPO 21% | Q77: 1326817699 (52.82€) | 1314692415 (363.99€)
A78: EXTRA_UE | B78: BEE MAILUP INC | C78: US | D78: IDEIN453916482 | E78: 32 | F78: 32 | G78: 3270.11 | H78: 3270.11 | I78: 2018 | J78: 2020 | K78: 112 | L78: 21% RC | M78: Extra-UE SaaS (review: posible nuevo tax) | P78: COMPRAS SERVICIOS TIPO 21% | Q78: INV72310 (90.96€) | INV68198 (90.96€)
A79: EXTRA_UE | B79: STITCH, INC | C79: US | D79: STITCH | E79: 27 | F79: 27 | G79: 2370.96 | H79: 2370.96 | I79: 2019 | J79: 2021 | K79: 112 | L79: 21% RC | M79: Extra-UE SaaS (review: posible nuevo tax) | P79: COMPRAS SERVICIOS TIPO 21% | Q79: INV00147823 (91.97€) | INV001385446 (93.78€)
A80: EXTRA_UE | B80: BEE MAILUP INC | C80: US | D80: EIN453916481 | E80: 12 | F80: 12 | G80: 1833.11 | H80: 1833.11 | I80: 2021 | J80: 2021 | K80: 112 | L80: 21% RC | M80: Extra-UE SaaS (review: posible nuevo tax) | P80: COMPRAS SERVICIOS TIPO 21% | Q80: 21Z00125328 (228.61€) | 21Z00115707 (223.72€)
A81: EXTRA_UE | B81: FIGMA, INC. | C81: US | D81: FIGMA | E81: 20 | F81: 20 | G81: 1181.16 | H81: 1181.16 | I81: 2020 | J81: 2021 | K81: 112 | L81: 21% RC | M81: Extra-UE SaaS (review: posible nuevo tax) | P81: COMPRAS SERVICIOS TIPO 21% | Q81: 793AC4330010 (37.99€) | 793AC4330009 (38.93€)
A82: EXTRA_UE | B82: BLENDO APRISE INC. | C82: US | D82: BLENDO | E82: 10 | F82: 10 | G82: 965.05 | H82: 965.05 | I82: 2018 | J82: 2018 | K82: 112 | L82: 21% RC | M82: Extra-UE SaaS (review: posible nuevo tax) | P82: COMPRAS SERVICIOS TIPO 21% | Q82: IN1819 (90.96€) | IN1708 (89.35€)
A83: EXTRA_UE | B83: MIRO INC FORMERLY REALTIMEBOARD | C83: US | D83: USEIN463921926 | E83: 21 | F83: 21 | G83: 927.94 | H83: 927.94 | I83: 2020 | J83: 2021 | K83: 112 | L83: 21% RC | M83: Extra-UE SaaS (review: posible nuevo tax) | P83: COMPRAS SERVICIOS TIPO 21% | Q83: 27BE2F310009 (42.41€) | 27BE2F310008 (43.59€)
A84: EXTRA_UE | B84: CALENDLY LLC | C84: US | D84: CALENDLY | E84: 28 | F84: 28 | G84: 858.55 | H84: 858.55 | I84: 2019 | J84: 2021 | K84: 112 | L84: 21% RC | M84: Extra-UE SaaS (review: posible nuevo tax) | P84: COMPRAS SERVICIOS TIPO 21% | Q84: 24303373 (14.04€) | 9F58FC550005 (13.88€)
A85: EXTRA_UE | B85: PLATZI INC | C85: US | D85: PLATZI | E85: 15 | F85: 15 | G85: 752.11 | H85: 752.11 | I85: 2018 | J85: 2020 | K85: 112 | L85: 21% RC | M85: Extra-UE SaaS (review: posible nuevo tax) | P85: COMPRAS SERVICIOS TIPO 21% | Q85: 257242 (34.57€) | 252051 (34.57€)
A86: EXTRA_UE | B86: IMGIX | C86: US | D86: IMGIX | E86: 50 | F86: 50 | G86: 604.88 | H86: 604.88 | I86: 2018 | J86: 2021 | K86: 112 | L86: 21% RC | M86: Extra-UE SaaS (review: posible nuevo tax) | P86: COMPRAS SERVICIOS TIPO 21% | Q86: 094184 (12.35€) | 0090347 (12.45€)
A87: EXTRA_UE | B87: SCREENCONNECT SOFTWARE, LLC | C87: US | D87: SCREENCONNECT | E87: 2 | F87: 2 | G87: 590.71 | H87: 590.71 | I87: 2018 | J87: 2020 | K87: 112 | L87: 21% RC | M87: Extra-UE SaaS (review: posible nuevo tax) | P87: COMPRAS SERVICIOS TIPO 21% | Q87: 180821134822 (108.21€) | 6142654908653388239 (482.5€)
A88: EXTRA_UE | B88: ZEPLIN INC. | C88: US | D88: ZEPLIN | E88: 3 | F88: 3 | G88: 547.66 | H88: 547.66 | I88: 2018 | J88: 2020 | K88: 112 | L88: 21% RC | M88: Extra-UE SaaS (review: posible nuevo tax) | P88: COMPRAS SERVICIOS TIPO 21% | Q88: LNCT6V (184.93€) | ZIJ2555LDKH6G (189.81€)
... A112: SIN_PAIS | B112: HONGKONG STAROC TECHNOLOGY CO.,LIMITED | C112: ?? | D112: STAROC | E112: 2 | F112: 2 | G112: 0 | H112: 0 | I112: 2019 | J112: 2020 | K112: 112 | L112: 21% RC | M112: Revisar pais (probable extra-UE) | P112: COMPRAS SERVICIOS TIPO 21% | Q112: INVFR139642611201910 (14.04€) | FR139642611201910883 (-14.04€)
A113: TOTAL | E113: =SUM(E2:E112) | F113: =SUM(F2:F112) | G113: =SUM(G2:G112) | H113: =SUM(H2:H112)
